intra/__init__.py
intra/example.py
intra-0.0.1.dist-info/licenses/LICENSE
intra-0.0.1.dist-info/WHEEL
intra-0.0.1.dist-info/METADATA
intra-0.0.1.dist-info/RECORD
